traffik/__init__.py
traffik/decorators.py
traffik/exceptions.py
traffik/middleware.py
traffik/py.typed
traffik/rates.py
traffik/throttles.py
traffik/types.py
traffik/utils.py
traffik/backends/__init__.py
traffik/backends/base.py
traffik/backends/inmemory.py
traffik/backends/memcached.py
traffik/backends/redis.py
traffik/strategies/__init__.py
traffik/strategies/fixed_window.py
traffik/strategies/leaky_bucket.py
traffik/strategies/sliding_window.py
traffik/strategies/token_bucket.py
traffik-1.0.0b1.dist-info/METADATA
traffik-1.0.0b1.dist-info/WHEEL
traffik-1.0.0b1.dist-info/licenses/LICENSE
traffik-1.0.0b1.dist-info/RECORD
