Metadata-Version: 2.4
Name: traffik
Version: 1.0.0b1
Summary: Distributed rate limiting for Starlette applications.
Project-URL: Homepage, https://github.com/ti-oluwa/traffik
Project-URL: Documentation, https://github.com/ti-oluwa/traffik#readme
Project-URL: Repository, https://github.com/ti-oluwa/traffik.git
Project-URL: Bug Tracker, https://github.com/ti-oluwa/traffik/issues
Project-URL: Changelog, https://github.com/ti-oluwa/traffik/blob/main/CHANGELOG.md
Author-email: tioluwa <tioluwa.dev@gmail.com>
Maintainer-email: tioluwa <tioluwa.dev@gmail.com>
License: MIT License
License-File: LICENSE
Keywords: api,distributed-rate-limiting,fastapi,rate-limiting,starlette,throttling
Classifier: Development Status :: 4 - Beta
Classifier: Framework :: FastAPI
Classifier: Intended Audience :: Developers
Classifier: License :: OSI Approved :: MIT License
Classifier: Operating System :: OS Independent
Classifier: Programming Language :: Python :: 3
Classifier: Programming Language :: Python :: 3.9
Classifier: Programming Language :: Python :: 3.10
Classifier: Programming Language :: Python :: 3.11
Classifier: Programming Language :: Python :: 3.12
Classifier: Programming Language :: Python :: 3.13
Classifier: Topic :: Internet :: WWW/HTTP
Classifier: Topic :: Software Development :: Libraries :: Python Modules
Classifier: Topic :: System :: Networking
Requires-Python: >=3.9
Requires-Dist: annotated-types>=0.7.0
Requires-Dist: starlette>=0.14.0
Provides-Extra: all
Requires-Dist: aiomcache>=0.8.2; extra == 'all'
Requires-Dist: pottery>=3.0.1; extra == 'all'
Requires-Dist: redis>=5.0.0; extra == 'all'
Provides-Extra: dev
Requires-Dist: aiomcache>=0.8.2; extra == 'dev'
Requires-Dist: anyio>=4.0.0; extra == 'dev'
Requires-Dist: bandit>=1.7.10; extra == 'dev'
Requires-Dist: fastapi>=0.68.0; extra == 'dev'
Requires-Dist: httpx>=0.28.0; extra == 'dev'
Requires-Dist: mypy>=1.14.1; extra == 'dev'
Requires-Dist: orjson>=3.11.3; extra == 'dev'
Requires-Dist: pottery>=3.0.1; extra == 'dev'
Requires-Dist: pytest-asyncio>=0.24.0; extra == 'dev'
Requires-Dist: pytest-cov>=5.0.0; extra == 'dev'
Requires-Dist: pytest-watch>=4.2.0; extra == 'dev'
Requires-Dist: pytest>=8.0.0; extra == 'dev'
Requires-Dist: redis>=5.0.0; extra == 'dev'
Requires-Dist: requests>=2.32.4; extra == 'dev'
Requires-Dist: ruff>=0.12.1; extra == 'dev'
Provides-Extra: memcached
Requires-Dist: aiomcache>=0.8.2; extra == 'memcached'
Provides-Extra: redis
Requires-Dist: pottery>=3.0.1; extra == 'redis'
Requires-Dist: redis>=5.0.0; extra == 'redis'
Provides-Extra: test
Requires-Dist: aiomcache>=0.8.2; extra == 'test'
Requires-Dist: anyio>=4.0.0; extra == 'test'
Requires-Dist: fastapi>=0.68.0; extra == 'test'
Requires-Dist: httpx>=0.28.0; extra == 'test'
Requires-Dist: pottery>=3.0.1; extra == 'test'
Requires-Dist: pytest-asyncio>=0.24.0; extra == 'test'
Requires-Dist: pytest-cov>=5.0.0; extra == 'test'
Requires-Dist: pytest>=8.0.0; extra == 'test'
Requires-Dist: redis>=5.0.0; extra == 'test'
Requires-Dist: requests>=2.32.4; extra == 'test'
